tabqa/__init__.py
tabqa/myfunctions.py
tabqa-0.1.3.dist-info/METADATA
tabqa-0.1.3.dist-info/WHEEL
tabqa-0.1.3.dist-info/top_level.txt
tabqa-0.1.3.dist-info/RECORD
