Metadata-Version: 2.1
Name: tabqa
Version: 0.1.3
Summary: This Python package provides functions to convert natural language to SQL queries using a pre-trained language model.
Author: Ketan More
Requires-Dist: torch
Requires-Dist: transformers
Requires-Dist: bitsandbytes
Requires-Dist: accelerate
Requires-Dist: sqlparse
